torch_ort/__init__.py
torch_ort/_version.py
torch_ort/configure/__main__.py
torch_ort/ortinferencemodule/__init__.py
torch_ort/ortinferencemodule/_utils_infer.py
torch_ort/ortinferencemodule/ortinferencemodule.py
torch_ort/ortinferencemodule/provider_options.py
torch_ort_infer-1.13.1.dist-info/METADATA
torch_ort_infer-1.13.1.dist-info/WHEEL
torch_ort_infer-1.13.1.dist-info/top_level.txt
torch_ort_infer-1.13.1.dist-info/RECORD
