Metadata-Version: 2.1
Name: torch-ort-infer
Version: 1.13.1
Summary: Accelerate PyTorch models with ONNX Runtime OpenVINO EP
Home-page: https://github.com/pytorch/ort
Author: torch-ort contributors
Project-URL: Bug Tracker, https://github.com/pytorch/ort/issues
Classifier: Programming Language :: Python :: 3
Classifier: License :: OSI Approved :: MIT License
Classifier: Operating System :: OS Independent
Requires-Python: >=3.7
Requires-Dist: onnxruntime-openvino (>=1.12.0)
Requires-Dist: torch (==1.12.1)
Provides-Extra: openvino
Requires-Dist: onnxruntime-openvino (>=1.12.0) ; extra == 'openvino'
